st_link_analysis/__init__.py
st_link_analysis/component/__init__.py
st_link_analysis/component/component.py
st_link_analysis/component/events.py
st_link_analysis/component/icons.py
st_link_analysis/component/layouts.py
st_link_analysis/component/styles.py
st_link_analysis/frontend/build/32b01d6a21d9433a251c.ttf
st_link_analysis/frontend/build/apache-arrow.5ff78659df0206a54579.bundle.js
st_link_analysis/frontend/build/cytoscape.7a9ca86f3f5dd910655f.bundle.js
st_link_analysis/frontend/build/cytoscape.7a9ca86f3f5dd910655f.bundle.js.LICENSE.txt
st_link_analysis/frontend/build/index.34ae10892539aa3c9e1b.bundle.js
st_link_analysis/frontend/build/index.html
st_link_analysis/frontend/build/runtime.db0e8c71a2ba7ab84dcf.bundle.js
st_link_analysis/frontend/build/streamlit-component-lib.867ddc344c0ff22a24ae.bundle.js
st_link_analysis/frontend/build/vendors.ad9f4ec49698516014ca.bundle.js
st_link_analysis/frontend/build/vendors.ad9f4ec49698516014ca.bundle.js.LICENSE.txt
st_link_analysis/frontend/build/icons/account_balance.svg
st_link_analysis/frontend/build/icons/alternate_email.svg
st_link_analysis/frontend/build/icons/analytics.svg
st_link_analysis/frontend/build/icons/assured_workload.svg
st_link_analysis/frontend/build/icons/badge.svg
st_link_analysis/frontend/build/icons/business.svg
st_link_analysis/frontend/build/icons/campaign.svg
st_link_analysis/frontend/build/icons/cell_tower.svg
st_link_analysis/frontend/build/icons/chat.svg
st_link_analysis/frontend/build/icons/cloud.svg
st_link_analysis/frontend/build/icons/credit_card.svg
st_link_analysis/frontend/build/icons/description.svg
st_link_analysis/frontend/build/icons/directions_car.svg
st_link_analysis/frontend/build/icons/dns.svg
st_link_analysis/frontend/build/icons/email.svg
st_link_analysis/frontend/build/icons/factory.svg
st_link_analysis/frontend/build/icons/flag.svg
st_link_analysis/frontend/build/icons/flight.svg
st_link_analysis/frontend/build/icons/folder.svg
st_link_analysis/frontend/build/icons/group.svg
st_link_analysis-0.4.0.dist-info/METADATA
st_link_analysis-0.4.0.dist-info/WHEEL
st_link_analysis-0.4.0.dist-info/licenses/LICENSE
st_link_analysis-0.4.0.dist-info/RECORD
