Metadata-Version: 2.4
Name: st_link_analysis
Version: 0.4.0
Summary: A streamlit custom component for visualizing and interacting with graphs
Project-URL: Homepage, https://github.com/AlrasheedA/st-link-analysis
Project-URL: Issues, https://github.com/AlrasheedA/st-link-analysis/issues
Author: AlrasheedA
License-Expression: MIT
License-File: LICENSE
Keywords: cytoscape,graph,link analysis,streamlit
Classifier: License :: OSI Approved :: MIT License
Classifier: Operating System :: OS Independent
Classifier: Programming Language :: Python :: 3
Classifier: Programming Language :: Python :: 3.9
Classifier: Programming Language :: Python :: 3.10
Classifier: Programming Language :: Python :: 3.11
Classifier: Programming Language :: Python :: 3.12
Requires-Python: >=3.9
Requires-Dist: streamlit>=0.63
Provides-Extra: dev
Requires-Dist: mypy; extra == 'dev'
Requires-Dist: pytest; extra == 'dev'
Requires-Dist: pytest-playwright; extra == 'dev'
Requires-Dist: pytest-rerunfailures; extra == 'dev'
Requires-Dist: ruff; extra == 'dev'
